{
  "parent": "minecraft:recipes/root",
  "rewards": {
    "recipes": [
      "hplus:upgrade_speed_high"
    ]
  },
  "criteria": {
    "has_speed_upgrade": {
      "trigger": "minecraft:inventory_changed",
      "conditions": {
        "items": [
          {
            "items": [
              "hplus:upgrade_speed"
            ]
          }
        ]
      }
    },
    "has_the_recipe": {
      "trigger": "minecraft:recipe_unlocked",
      "conditions": {
        "recipe": "hplus:upgrade_speed_high"
      }
    }
  },
  "requirements": [
    [
      "has_speed_upgrade",
      "has_the_recipe"
    ]
  ]
}